{
  "_class": "group",
  "booleanOperation": -1,
  "clippingMaskMode": 0,
  "do_objectID": "B298B7DE-758D-44C1-8D85-57E7FB193D5D",
  "exportOptions": {
    "_class": "exportOptions",
    "do_objectID": "11189E23-F894-4A53-B99D-A6B804AAAB0B",
    "exportFormats": [
    ],
    "includedLayerIds": [
    ],
    "layerOptions": 0,
    "shouldTrim": false
  },
  "frame": {
    "_class": "rect",
    "constrainProportions": false,
    "do_objectID": "BF737114-89C2-4162-914F-1544BF074F81",
    "height": 21,
    "width": 113,
    "x": 124,
    "y": 616
  },
  "groupLayout": {
    "_class": "MSImmutableFreeformGroupLayout",
    "do_objectID": "C9929ACA-B07A-4569-AF94-1D53B0704980"
  },
  "hasClickThrough": false,
  "hasClippingMask": false,
  "isFixedToViewport": false,
  "isFlippedHorizontal": false,
  "isFlippedVertical": false,
  "isLocked": false,
  "isVisible": true,
  "layerListExpandedType": 0,
  "layers": [
    {
      "class": "text",
      "id": "43DA7731-603F-4C72-B29F-A37988A1ED81"
    },
    {
      "class": "oval",
      "id": "48AD9020-12BC-4827-823A-70845441ED60"
    }
  ],
  "name": "Radio Copy 2",
  "nameIsFixed": true,
  "resizingConstraint": 63,
  "resizingType": 0,
  "rotation": 0,
  "shouldBreakMaskChain": false,
  "style": {
    "_class": "style",
    "borderOptions": {
      "_class": "borderOptions",
      "dashPattern": [
      ],
      "do_objectID": "32268CB0-A04C-4C3B-BAAC-F3823B806DF4",
      "isEnabled": true,
      "lineCapStyle": 0,
      "lineJoinStyle": 0
    },
    "do_objectID": "559A8195-963F-47BB-BA61-002893F84F78",
    "endMarkerType": 0,
    "miterLimit": 10,
    "startMarkerType": 0,
    "windingRule": 1
  }
}