{
  "_class": "group",
  "booleanOperation": -1,
  "clippingMaskMode": 0,
  "do_objectID": "A48BD2B9-3B1A-4136-B8CD-9C8696944A1B",
  "exportOptions": {
    "_class": "exportOptions",
    "exportFormats": [
    ],
    "includedLayerIds": [
    ],
    "layerOptions": 0,
    "shouldTrim": false
  },
  "frame": {
    "_class": "rect",
    "constrainProportions": false,
    "height": 406,
    "width": 320,
    "x": 0,
    "y": 0
  },
  "groupLayout": {
    "_class": "MSImmutableFreeformGroupLayout"
  },
  "hasClickThrough": false,
  "hasClippingMask": false,
  "isFixedToViewport": false,
  "isFlippedHorizontal": false,
  "isFlippedVertical": false,
  "isLocked": false,
  "isVisible": true,
  "layerListExpandedType": 0,
  "layers": [
    {
      "class": "group",
      "id": "647E6C26-071C-476C-91CE-5DA367823D0D"
    },
    {
      "class": "text",
      "id": "1A0F11BA-8DF6-4DB8-B2F1-C39E6F78261D"
    },
    {
      "class": "rectangle",
      "id": "F4EF077D-D539-4850-83EF-1FA0898D5F76"
    },
    {
      "class": "text",
      "id": "023B622B-A7B4-4C53-A8BF-9356EB78227E"
    },
    {
      "class": "text",
      "id": "0A07F208-9D51-461B-9EDA-ECA23EEC9C38"
    },
    {
      "class": "group",
      "id": "B481E175-40E3-491A-AC45-E307BE51E53D"
    },
    {
      "class": "text",
      "id": "A52A036A-168D-40E5-A2F0-DBD4003E86D4"
    }
  ],
  "name": "SectionDesc",
  "nameIsFixed": true,
  "resizingConstraint": 63,
  "resizingType": 0,
  "rotation": 0,
  "shouldBreakMaskChain": false,
  "style": {
    "_class": "style",
    "blur": {
      "_class": "blur",
      "center": "{0.5, 0.5}",
      "isEnabled": false,
      "motionAngle": 0,
      "radius": 10,
      "saturation": 1,
      "type": 0
    },
    "borderOptions": {
      "_class": "borderOptions",
      "dashPattern": [
      ],
      "isEnabled": true,
      "lineCapStyle": 0,
      "lineJoinStyle": 0
    },
    "borders": [
    ],
    "colorControls": {
      "_class": "colorControls",
      "brightness": 0,
      "contrast": 1,
      "hue": 0,
      "isEnabled": false,
      "saturation": 1
    },
    "contextSettings": {
      "_class": "graphicsContextSettings",
      "blendMode": 0,
      "opacity": 1
    },
    "do_objectID": "B0B169A6-5DFE-44D3-893A-5D1BF0FCC38D",
    "endMarkerType": 0,
    "fills": [
    ],
    "innerShadows": [
    ],
    "miterLimit": 10,
    "shadows": [
    ],
    "startMarkerType": 0,
    "windingRule": 1
  }
}