{
  "_class": "group",
  "booleanOperation": -1,
  "clippingMaskMode": 0,
  "do_objectID": "BD3550E6-A184-4313-ADA8-24F2C5397F98",
  "exportOptions": {
    "_class": "exportOptions",
    "do_objectID": "255E1128-EBBC-4039-8A93-8163103FAEEC",
    "exportFormats": [
    ],
    "includedLayerIds": [
    ],
    "layerOptions": 0,
    "shouldTrim": false
  },
  "frame": {
    "_class": "rect",
    "constrainProportions": false,
    "do_objectID": "F4646D0E-2760-4131-97D4-12F3F21289E9",
    "height": 64,
    "width": 413,
    "x": 272,
    "y": 268.9284090909091
  },
  "groupLayout": {
    "_class": "MSImmutableFreeformGroupLayout",
    "do_objectID": "8B093291-7B69-4163-A477-278510220F21"
  },
  "hasClickThrough": false,
  "hasClippingMask": false,
  "isFixedToViewport": false,
  "isFlippedHorizontal": false,
  "isFlippedVertical": false,
  "isLocked": false,
  "isVisible": true,
  "layerListExpandedType": 0,
  "layers": [
    {
      "class": "text",
      "id": "EC549A50-77EA-493E-A83A-01A6C2493C10"
    },
    {
      "class": "text",
      "id": "97B112B1-964D-436B-B40C-D47CAADD2D06"
    }
  ],
  "name": "Group 2",
  "nameIsFixed": false,
  "resizingConstraint": 63,
  "resizingType": 0,
  "rotation": 0,
  "shouldBreakMaskChain": false,
  "style": {
    "_class": "style",
    "borderOptions": {
      "_class": "borderOptions",
      "dashPattern": [
      ],
      "do_objectID": "57EB0496-02B2-4C99-A0CA-6171F0906ED9",
      "isEnabled": true,
      "lineCapStyle": 0,
      "lineJoinStyle": 0
    },
    "do_objectID": "CA192282-7AF2-4371-9561-7032988DE4AE",
    "endMarkerType": 0,
    "miterLimit": 10,
    "startMarkerType": 0,
    "windingRule": 1
  }
}