{
  "_class": "text",
  "attributedString": {
    "_class": "attributedString",
    "attributes": [
      {
        "_class": "stringAttribute",
        "attributes": {
          "MSAttributedStringColorAttribute": {
            "_class": "color",
            "alpha": 1,
            "blue": 0.4784313725490196,
            "green": 0.4196078431372549,
            "red": 0.4196078431372549
          },
          "MSAttributedStringFontAttribute": {
            "_class": "UIFontDescriptor",
            "attributes": {
              "name": "Sarabun-Regular",
              "size": 13
            }
          },
          "paragraphStyle": {
            "_class": "paragraphStyle"
          }
        },
        "length": 163,
        "location": 0
      }
    ],
    "string": "Elige en el calendario los días que estarás de vacaciones.\nA tu regreso, no olvides dejar tiempo suficiente para que puedas elaborar y entregar tus nuevas órdenes."
  },
  "automaticallyDrawOnUnderlyingPath": false,
  "booleanOperation": -1,
  "clippingMaskMode": 0,
  "do_objectID": "8272CA5A-974E-46FA-972E-4FBF310025A0",
  "dontSynchroniseWithSymbol": false,
  "exportOptions": {
    "_class": "exportOptions",
    "do_objectID": "3111B480-9CA9-41D8-81C9-851CF492472F",
    "exportFormats": [
    ],
    "includedLayerIds": [
    ],
    "layerOptions": 0,
    "shouldTrim": false
  },
  "frame": {
    "_class": "rect",
    "constrainProportions": false,
    "do_objectID": "4555A38E-7345-413E-BBB9-2559691190DC",
    "height": 85,
    "width": 279,
    "x": 0,
    "y": 27
  },
  "glyphBounds": "{{0, 4}, {266, 79}}",
  "hasClippingMask": false,
  "isFixedToViewport": false,
  "isFlippedHorizontal": false,
  "isFlippedVertical": false,
  "isLocked": false,
  "isVisible": true,
  "layerListExpandedType": 0,
  "lineSpacingBehaviour": 3,
  "name": "Elige en el calendar",
  "nameIsFixed": false,
  "resizingConstraint": 63,
  "resizingType": 0,
  "rotation": 0,
  "sharedStyleID": "97E6DC11-8279-457A-95EB-86BDDE8759D3",
  "shouldBreakMaskChain": false,
  "style": {
    "_class": "style",
    "borderOptions": {
      "_class": "borderOptions",
      "dashPattern": [
      ],
      "do_objectID": "28FC7309-F6B3-4669-8A38-D13D20FB75BC",
      "isEnabled": true,
      "lineCapStyle": 0,
      "lineJoinStyle": 0
    },
    "do_objectID": "B4F9C0B5-7450-451B-9F70-70B845F2A6B7",
    "endMarkerType": 0,
    "miterLimit": 10,
    "startMarkerType": 0,
    "textStyle": {
      "_class": "textStyle",
      "do_objectID": "F851F932-FE3C-4515-A793-6B8CEDAA5A12",
      "encodedAttributes": {
        "MSAttributedStringColorAttribute": {
          "_class": "color",
          "alpha": 1,
          "blue": 0.4784313725490196,
          "green": 0.4196078431372549,
          "red": 0.4196078431372549
        },
        "MSAttributedStringFontAttribute": {
          "_class": "UIFontDescriptor",
          "attributes": {
            "name": "Sarabun-Regular",
            "size": 13
          }
        },
        "paragraphStyle": {
          "_class": "paragraphStyle"
        }
      },
      "verticalAlignment": 0
    },
    "windingRule": 1
  },
  "textBehaviour": 1
}