{
  "_class": "artboard",
  "backgroundColor": {
    "_class": "color",
    "alpha": 1,
    "blue": 1,
    "green": 1,
    "red": 1
  },
  "booleanOperation": -1,
  "clippingMaskMode": 0,
  "do_objectID": "79F70ECD-BF97-4B9D-9B02-31A42931E135",
  "exportOptions": {
    "_class": "exportOptions",
    "exportFormats": [
    ],
    "includedLayerIds": [
    ],
    "layerOptions": 0,
    "shouldTrim": false
  },
  "frame": {
    "_class": "rect",
    "constrainProportions": false,
    "height": 568,
    "width": 320,
    "x": 1657,
    "y": -1865
  },
  "groupLayout": {
    "_class": "MSImmutableFreeformGroupLayout"
  },
  "hasBackgroundColor": true,
  "hasClickThrough": false,
  "hasClippingMask": false,
  "horizontalRulerData": {
    "_class": "rulerData",
    "base": 0,
    "guides": [
      10,
      299,
      20,
      310
    ]
  },
  "includeBackgroundColorInExport": true,
  "includeInCloudUpload": true,
  "isFixedToViewport": false,
  "isFlippedHorizontal": false,
  "isFlippedVertical": false,
  "isFlowHome": false,
  "isLocked": false,
  "isVisible": true,
  "layerListExpandedType": 2,
  "layers": [
    {
      "class": "bitmap",
      "id": "7B60309D-FB77-49D7-B5A4-298E3AD75726"
    },
    {
      "class": "group",
      "id": "4BD80C8E-7933-4B95-A965-3990B9D4A6C4"
    },
    {
      "class": "group",
      "id": "4BCCD806-630E-40B7-B358-630D4847BE1F"
    },
    {
      "class": "shapePath",
      "id": "55F46232-B089-4456-ABF1-731BDD6220A7"
    },
    {
      "class": "symbolInstance",
      "id": "D31EAC65-C164-4F08-901D-FD86FE9BCFAE"
    },
    {
      "class": "group",
      "id": "8072385E-8381-4E6D-97C5-37C50B663D68"
    },
    {
      "class": "text",
      "id": "EDF057D8-2050-4695-94DB-03562C935A93"
    },
    {
      "class": "group",
      "id": "78BE7C43-7537-4F0F-BCA7-718B816B5108"
    },
    {
      "class": "rectangle",
      "id": "240492A5-2DA1-44F1-BABF-1A40AD50ECE5"
    },
    {
      "class": "group",
      "id": "320EEF21-75F0-4176-87A5-3FC1ACBDE81A"
    },
    {
      "class": "rectangle",
      "id": "390B56D0-7C7F-4120-AF00-AA2E19B7B105"
    },
    {
      "class": "group",
      "id": "F5C0DA4E-EA6B-40AB-9C53-801B71D9D2F3"
    },
    {
      "class": "symbolInstance",
      "id": "86473A0C-9317-45DD-9BE4-BD18DB8AC5AC"
    },
    {
      "class": "rectangle",
      "id": "63E78F5F-950D-4EAD-8C0E-BE8FFFB065E3"
    },
    {
      "class": "group",
      "id": "F0C8A0C3-1B2F-4EDD-AD62-80BEFCB81FCD"
    }
  ],
  "name": "Phone/Category/modal",
  "nameIsFixed": true,
  "presetDictionary": {
    "allowResizedMatching": 0,
    "height": 1024,
    "name": "Mobile",
    "offersLandscapeVariant": 1,
    "width": 320
  },
  "resizesContent": false,
  "resizingConstraint": 63,
  "resizingType": 0,
  "rotation": 0,
  "shouldBreakMaskChain": true,
  "style": {
    "_class": "style",
    "blur": {
      "_class": "blur",
      "center": "{0.5, 0.5}",
      "isEnabled": false,
      "motionAngle": 0,
      "radius": 10,
      "saturation": 1,
      "type": 0
    },
    "borderOptions": {
      "_class": "borderOptions",
      "dashPattern": [
      ],
      "isEnabled": true,
      "lineCapStyle": 0,
      "lineJoinStyle": 0
    },
    "borders": [
    ],
    "colorControls": {
      "_class": "colorControls",
      "brightness": 0,
      "contrast": 1,
      "hue": 0,
      "isEnabled": false,
      "saturation": 1
    },
    "contextSettings": {
      "_class": "graphicsContextSettings",
      "blendMode": 0,
      "opacity": 1
    },
    "do_objectID": "D3DAA678-1CEC-4F2A-B604-FE6BB0895956",
    "endMarkerType": 0,
    "fills": [
    ],
    "innerShadows": [
    ],
    "miterLimit": 10,
    "shadows": [
    ],
    "startMarkerType": 0,
    "windingRule": 1
  },
  "verticalRulerData": {
    "_class": "rulerData",
    "base": 0,
    "guides": [
      29
    ]
  }
}