{
  "_class": "group",
  "booleanOperation": -1,
  "clippingMaskMode": 0,
  "do_objectID": "A57B6EA5-FFA4-460F-A73A-8B2EA5718D9D",
  "exportOptions": {
    "_class": "exportOptions",
    "do_objectID": "A935A271-826B-4F8C-AED0-76EC4A068E94",
    "exportFormats": [
    ],
    "includedLayerIds": [
    ],
    "layerOptions": 0,
    "shouldTrim": false
  },
  "frame": {
    "_class": "rect",
    "constrainProportions": false,
    "do_objectID": "66FA39ED-264E-402F-8948-FA252BA50B2F",
    "height": 41,
    "width": 91,
    "x": 400.4765624999995,
    "y": 890.5668016194331
  },
  "groupLayout": {
    "_class": "MSImmutableFreeformGroupLayout",
    "do_objectID": "34B15B3D-C92C-48FF-BE3B-04D43C465FE3"
  },
  "hasClickThrough": false,
  "hasClippingMask": false,
  "isFixedToViewport": false,
  "isFlippedHorizontal": false,
  "isFlippedVertical": false,
  "isLocked": false,
  "isVisible": true,
  "layerListExpandedType": 0,
  "layers": [
    {
      "class": "rectangle",
      "id": "6CB58899-D14F-47E9-961E-A193BF9A472C"
    },
    {
      "class": "text",
      "id": "A0E39019-143B-4888-B0EA-161E81C9D95D"
    }
  ],
  "name": "Categorybutton Copy",
  "nameIsFixed": true,
  "resizingConstraint": 63,
  "resizingType": 0,
  "rotation": 0,
  "shouldBreakMaskChain": false,
  "style": {
    "_class": "style",
    "borderOptions": {
      "_class": "borderOptions",
      "dashPattern": [
      ],
      "do_objectID": "2EE0B448-199F-4FC7-A1A9-6573A5C5D10E",
      "isEnabled": true,
      "lineCapStyle": 0,
      "lineJoinStyle": 0
    },
    "do_objectID": "944466C5-9CCA-4019-ABD6-9C3E701115C5",
    "endMarkerType": 0,
    "miterLimit": 10,
    "startMarkerType": 0,
    "windingRule": 1
  }
}