{
  "_class": "group",
  "booleanOperation": -1,
  "clippingMaskMode": 0,
  "do_objectID": "BA9DDB59-C6C6-407F-BD89-F82076DB47A5",
  "exportOptions": {
    "_class": "exportOptions",
    "do_objectID": "13F88453-96A6-4AD7-9FC0-B6F0676EE9DB",
    "exportFormats": [
    ],
    "includedLayerIds": [
    ],
    "layerOptions": 0,
    "shouldTrim": false
  },
  "frame": {
    "_class": "rect",
    "constrainProportions": false,
    "do_objectID": "F3E1E001-84C2-4B60-9EB2-D97FDCF0D50C",
    "height": 40,
    "width": 220,
    "x": 41,
    "y": 229
  },
  "groupLayout": {
    "_class": "MSImmutableFreeformGroupLayout",
    "do_objectID": "6199A4F9-8A9B-44BF-9635-B260367CCE19"
  },
  "hasClickThrough": false,
  "hasClippingMask": false,
  "isFixedToViewport": false,
  "isFlippedHorizontal": false,
  "isFlippedVertical": false,
  "isLocked": false,
  "isVisible": true,
  "layerListExpandedType": 0,
  "layers": [
    {
      "class": "text",
      "id": "B7A332CD-74F3-4909-B47F-AAFAAA937316"
    },
    {
      "class": "group",
      "id": "DE239406-71BA-43F9-B55E-C3B55D7C6688"
    }
  ],
  "name": "Quantity",
  "nameIsFixed": true,
  "resizingConstraint": 63,
  "resizingType": 0,
  "rotation": 0,
  "shouldBreakMaskChain": false,
  "style": {
    "_class": "style",
    "borderOptions": {
      "_class": "borderOptions",
      "dashPattern": [
      ],
      "do_objectID": "9E53A654-9587-4FC5-AA47-229769A34D1A",
      "isEnabled": true,
      "lineCapStyle": 0,
      "lineJoinStyle": 0
    },
    "do_objectID": "C7A9B98F-775E-4E23-B35E-28BB2580744D",
    "endMarkerType": 0,
    "miterLimit": 10,
    "startMarkerType": 0,
    "windingRule": 1
  }
}