{
  "_class": "group",
  "booleanOperation": -1,
  "clippingMaskMode": 0,
  "do_objectID": "B6D4D0DD-D8E6-4976-9175-4FB928074720",
  "exportOptions": {
    "_class": "exportOptions",
    "do_objectID": "530B9A5C-F5A2-4936-B71A-705A8A8377D4",
    "exportFormats": [
    ],
    "includedLayerIds": [
    ],
    "layerOptions": 0,
    "shouldTrim": false
  },
  "frame": {
    "_class": "rect",
    "constrainProportions": false,
    "do_objectID": "C4A3482A-2F09-467F-88D5-8461BAAC3A68",
    "height": 64,
    "width": 300,
    "x": 10,
    "y": -192.0715909090909
  },
  "groupLayout": {
    "_class": "MSImmutableFreeformGroupLayout",
    "do_objectID": "D0807F7B-C15F-4478-ADCD-98DAE57E4DCB"
  },
  "hasClickThrough": false,
  "hasClippingMask": false,
  "isFixedToViewport": false,
  "isFlippedHorizontal": false,
  "isFlippedVertical": false,
  "isLocked": false,
  "isVisible": true,
  "layerListExpandedType": 0,
  "layers": [
    {
      "class": "text",
      "id": "B00B62FD-C3BC-49A6-93E6-5044DC7FBF97"
    },
    {
      "class": "text",
      "id": "8F3AA227-C1B2-493A-8984-EC9568A8A49A"
    }
  ],
  "name": "Group 2",
  "nameIsFixed": false,
  "resizingConstraint": 63,
  "resizingType": 0,
  "rotation": 0,
  "shouldBreakMaskChain": false,
  "style": {
    "_class": "style",
    "borderOptions": {
      "_class": "borderOptions",
      "dashPattern": [
      ],
      "do_objectID": "EC6B1879-4962-41E1-8AC9-EC0B51CA8D86",
      "isEnabled": true,
      "lineCapStyle": 0,
      "lineJoinStyle": 0
    },
    "do_objectID": "3BCDB6B8-A533-4CD1-9053-354BEEFEFD70",
    "endMarkerType": 0,
    "miterLimit": 10,
    "startMarkerType": 0,
    "windingRule": 1
  }
}