{
  "_class": "group",
  "booleanOperation": -1,
  "clippingMaskMode": 0,
  "do_objectID": "D90F1257-FD01-41FE-AED1-75C1056C06C9",
  "exportOptions": {
    "_class": "exportOptions",
    "do_objectID": "D43F6335-050C-492E-AC8B-0D5D25E7F059",
    "exportFormats": [
    ],
    "includedLayerIds": [
    ],
    "layerOptions": 0,
    "shouldTrim": false
  },
  "frame": {
    "_class": "rect",
    "constrainProportions": false,
    "do_objectID": "9E628201-2F7B-42A1-B701-61BAEDB110D8",
    "height": 41,
    "width": 132,
    "x": 0,
    "y": 126
  },
  "groupLayout": {
    "_class": "MSImmutableFreeformGroupLayout",
    "do_objectID": "5FFB7007-C9FF-4F62-A773-B253A4939C41"
  },
  "hasClickThrough": false,
  "hasClippingMask": false,
  "isFixedToViewport": false,
  "isFlippedHorizontal": false,
  "isFlippedVertical": false,
  "isLocked": false,
  "isVisible": true,
  "layerListExpandedType": 1,
  "layers": [
    {
      "class": "rectangle",
      "id": "DC317891-5F62-4B64-8F9F-29784E483D55"
    },
    {
      "class": "text",
      "id": "8E8FE02F-3AD3-435E-84BB-328BBEDA8425"
    }
  ],
  "name": "Categorybutton",
  "nameIsFixed": true,
  "resizingConstraint": 63,
  "resizingType": 0,
  "rotation": 0,
  "shouldBreakMaskChain": false,
  "style": {
    "_class": "style",
    "borderOptions": {
      "_class": "borderOptions",
      "dashPattern": [
      ],
      "do_objectID": "403158FC-757C-4837-9F6E-3466FB3590BC",
      "isEnabled": true,
      "lineCapStyle": 0,
      "lineJoinStyle": 0
    },
    "do_objectID": "B21AE1DA-0D24-4DFA-B166-63F1FA1B5757",
    "endMarkerType": 0,
    "miterLimit": 10,
    "startMarkerType": 0,
    "windingRule": 1
  }
}