{
  "_class": "group",
  "booleanOperation": -1,
  "clippingMaskMode": 0,
  "do_objectID": "500368BB-8C14-452D-B23E-2C1B1E28C055",
  "exportOptions": {
    "_class": "exportOptions",
    "do_objectID": "64AE0E6B-0DD1-497F-8D97-B10AFFA5472D",
    "exportFormats": [
    ],
    "includedLayerIds": [
    ],
    "layerOptions": 0,
    "shouldTrim": false
  },
  "frame": {
    "_class": "rect",
    "constrainProportions": false,
    "do_objectID": "227D59EC-272D-43F1-9279-4F5CF5D55192",
    "height": 21,
    "width": 207,
    "x": 10,
    "y": 0
  },
  "groupLayout": {
    "_class": "MSImmutableFreeformGroupLayout",
    "do_objectID": "0AD8FC1F-7390-4D93-A4A4-24D9F05D4960"
  },
  "hasClickThrough": false,
  "hasClippingMask": false,
  "isFixedToViewport": false,
  "isFlippedHorizontal": false,
  "isFlippedVertical": false,
  "isLocked": false,
  "isVisible": true,
  "layerListExpandedType": 2,
  "layers": [
    {
      "class": "text",
      "id": "B9229C2E-1135-47D1-AEBF-F3196517CE7E"
    }
  ],
  "name": "Group 2 Copy",
  "nameIsFixed": false,
  "resizingConstraint": 63,
  "resizingType": 0,
  "rotation": 0,
  "shouldBreakMaskChain": false,
  "style": {
    "_class": "style",
    "borderOptions": {
      "_class": "borderOptions",
      "dashPattern": [
      ],
      "do_objectID": "CCEBE116-B54F-4AEE-AC72-83932B13B573",
      "isEnabled": true,
      "lineCapStyle": 0,
      "lineJoinStyle": 0
    },
    "do_objectID": "9423F70B-E1FA-4FB3-82E4-3EFD87208129",
    "endMarkerType": 0,
    "miterLimit": 10,
    "startMarkerType": 0,
    "windingRule": 1
  }
}