{
  "_class": "shapePath",
  "booleanOperation": -1,
  "clippingMaskMode": 0,
  "do_objectID": "640552A8-6028-4F97-9C03-A7BCAFA3BE66",
  "edited": true,
  "exportOptions": {
    "_class": "exportOptions",
    "do_objectID": "083AE907-FE9E-4402-B60A-DCED681AD72B",
    "exportFormats": [
    ],
    "includedLayerIds": [
    ],
    "layerOptions": 0,
    "shouldTrim": false
  },
  "frame": {
    "_class": "rect",
    "constrainProportions": false,
    "do_objectID": "BC18A83C-241C-4BB4-A2CB-29814033DE75",
    "height": 1,
    "width": 280,
    "x": 20,
    "y": 509.5
  },
  "hasClippingMask": false,
  "isClosed": false,
  "isFixedToViewport": false,
  "isFlippedHorizontal": false,
  "isFlippedVertical": false,
  "isLocked": false,
  "isVisible": true,
  "layerListExpandedType": 0,
  "name": "Line Copy",
  "nameIsFixed": false,
  "pointRadiusBehaviour": 1,
  "points": [
    {
      "_class": "curvePoint",
      "cornerRadius": 0,
      "curveFrom": "{-0.069642857142857104, 25.249999999999968}",
      "curveMode": 1,
      "curveTo": "{-0.069642857142857104, 25.249999999999968}",
      "hasCurveFrom": false,
      "hasCurveTo": false,
      "point": "{-5.1762909434950802e-18, 0.5}"
    },
    {
      "_class": "curvePoint",
      "cornerRadius": 0,
      "curveFrom": "{-0.069642857142857104, 25.249999999999968}",
      "curveMode": 1,
      "curveTo": "{-0.069642857142857104, 25.249999999999968}",
      "hasCurveFrom": false,
      "hasCurveTo": false,
      "point": "{1, 0.5}"
    }
  ],
  "resizingConstraint": 63,
  "resizingType": 0,
  "rotation": 0,
  "shouldBreakMaskChain": false,
  "style": {
    "_class": "style",
    "borderOptions": {
      "_class": "borderOptions",
      "dashPattern": [
      ],
      "do_objectID": "D32D7A4E-1E82-4D99-947D-686ED394D497",
      "isEnabled": true,
      "lineCapStyle": 2,
      "lineJoinStyle": 0
    },
    "borders": [
      {
        "_class": "border",
        "color": {
          "_class": "color",
          "alpha": 1,
          "blue": 0.8392156862745098,
          "green": 0.8470588235294118,
          "red": 0.8549019607843137
        },
        "fillType": 0,
        "isEnabled": true,
        "position": 0,
        "thickness": 1
      }
    ],
    "do_objectID": "1A1E1600-6A92-46E2-B730-3E3BA7A0208E",
    "endMarkerType": 0,
    "fills": [
      {
        "_class": "fill",
        "color": {
          "_class": "color",
          "alpha": 1,
          "blue": 0.847,
          "green": 0.847,
          "red": 0.847
        },
        "fillType": 0,
        "isEnabled": false,
        "noiseIndex": 0,
        "noiseIntensity": 0,
        "patternFillType": 1,
        "patternTileScale": 1
      }
    ],
    "miterLimit": 10,
    "startMarkerType": 0,
    "windingRule": 1
  }
}