{
  "_class": "group",
  "booleanOperation": -1,
  "clippingMaskMode": 0,
  "do_objectID": "7B953BA8-5C10-4EE4-BB7D-8260F43C8ED0",
  "exportOptions": {
    "_class": "exportOptions",
    "exportFormats": [
    ],
    "includedLayerIds": [
    ],
    "layerOptions": 0,
    "shouldTrim": false
  },
  "frame": {
    "_class": "rect",
    "constrainProportions": false,
    "height": 257,
    "width": 279,
    "x": 10,
    "y": 316
  },
  "groupLayout": {
    "_class": "MSImmutableFreeformGroupLayout"
  },
  "hasClickThrough": false,
  "hasClippingMask": false,
  "isFixedToViewport": false,
  "isFlippedHorizontal": false,
  "isFlippedVertical": false,
  "isLocked": false,
  "isVisible": true,
  "layerListExpandedType": 0,
  "layers": [
    {
      "class": "rectangle",
      "id": "FC9C9D50-1B16-4DC8-8F26-147CB38AFFA2"
    },
    {
      "class": "bitmap",
      "id": "F7D682EC-D7F7-4CC7-855E-3B21E0CA0080"
    },
    {
      "class": "text",
      "id": "CB255ED2-6F48-409D-A04C-0710BBCD0917"
    },
    {
      "class": "text",
      "id": "A82B1CDE-ECB7-4DD3-8C9A-AEDE9BDF9B1E"
    },
    {
      "class": "text",
      "id": "7ACA5241-F780-4BD4-A126-ED5339B271F8"
    },
    {
      "class": "group",
      "id": "A3217064-5E33-424E-B47A-77DDC50CBE5D"
    }
  ],
  "name": "ProductSize",
  "nameIsFixed": true,
  "resizingConstraint": 63,
  "resizingType": 0,
  "rotation": 0,
  "shouldBreakMaskChain": false,
  "style": {
    "_class": "style",
    "blur": {
      "_class": "blur",
      "center": "{0.5, 0.5}",
      "isEnabled": false,
      "motionAngle": 0,
      "radius": 10,
      "saturation": 1,
      "type": 0
    },
    "borderOptions": {
      "_class": "borderOptions",
      "dashPattern": [
      ],
      "isEnabled": true,
      "lineCapStyle": 0,
      "lineJoinStyle": 0
    },
    "borders": [
    ],
    "colorControls": {
      "_class": "colorControls",
      "brightness": 0,
      "contrast": 1,
      "hue": 0,
      "isEnabled": false,
      "saturation": 1
    },
    "contextSettings": {
      "_class": "graphicsContextSettings",
      "blendMode": 0,
      "opacity": 1
    },
    "do_objectID": "A5FF852D-F3E4-4376-9275-6DA01729E6F0",
    "endMarkerType": 0,
    "fills": [
    ],
    "innerShadows": [
    ],
    "miterLimit": 10,
    "shadows": [
    ],
    "startMarkerType": 0,
    "windingRule": 1
  }
}