{
  "_class": "text",
  "attributedString": {
    "_class": "attributedString",
    "attributes": [
      {
        "_class": "stringAttribute",
        "attributes": {
          "MSAttributedStringColorAttribute": {
            "_class": "color",
            "alpha": 1,
            "blue": 0.2431372549019608,
            "green": 0.2156862745098039,
            "red": 0.2156862745098039
          },
          "MSAttributedStringFontAttribute": {
            "_class": "UIFontDescriptor",
            "attributes": {
              "name": "Sarabun-SemiBold",
              "size": 16
            }
          },
          "paragraphStyle": {
            "_class": "paragraphStyle"
          }
        },
        "length": 23,
        "location": 0
      }
    ],
    "string": "TEMPORADA DE VACACIONES"
  },
  "automaticallyDrawOnUnderlyingPath": false,
  "booleanOperation": -1,
  "clippingMaskMode": 0,
  "do_objectID": "1A0FCDDC-FB6E-4273-87EC-784AF541CD80",
  "dontSynchroniseWithSymbol": false,
  "exportOptions": {
    "_class": "exportOptions",
    "do_objectID": "BB7A2752-B969-4395-A488-C5E66084D4EA",
    "exportFormats": [
    ],
    "includedLayerIds": [
    ],
    "layerOptions": 0,
    "shouldTrim": false
  },
  "frame": {
    "_class": "rect",
    "constrainProportions": false,
    "do_objectID": "AE512785-8733-4CB3-84F8-5448D2B375FC",
    "height": 21,
    "width": 241,
    "x": 0,
    "y": 0
  },
  "glyphBounds": "{{0, 5}, {210, 13}}",
  "hasClippingMask": false,
  "isFixedToViewport": false,
  "isFlippedHorizontal": false,
  "isFlippedVertical": false,
  "isLocked": false,
  "isVisible": true,
  "layerListExpandedType": 0,
  "lineSpacingBehaviour": 3,
  "name": "TEMPORADA DE VACACIO",
  "nameIsFixed": false,
  "resizingConstraint": 63,
  "resizingType": 0,
  "rotation": 0,
  "sharedStyleID": "C83C720E-B46B-4AEF-B622-1A4579B156D8",
  "shouldBreakMaskChain": false,
  "style": {
    "_class": "style",
    "borderOptions": {
      "_class": "borderOptions",
      "dashPattern": [
      ],
      "do_objectID": "8F030AE2-1864-4A4D-8319-0EE4F800289E",
      "isEnabled": true,
      "lineCapStyle": 0,
      "lineJoinStyle": 0
    },
    "do_objectID": "B3C19813-C16B-42D5-912D-C8516C19F5BF",
    "endMarkerType": 0,
    "miterLimit": 10,
    "startMarkerType": 0,
    "textStyle": {
      "_class": "textStyle",
      "do_objectID": "AD040617-5305-4004-B3A5-35E5679133F5",
      "encodedAttributes": {
        "MSAttributedStringColorAttribute": {
          "_class": "color",
          "alpha": 1,
          "blue": 0.2431372549019608,
          "green": 0.2156862745098039,
          "red": 0.2156862745098039
        },
        "MSAttributedStringFontAttribute": {
          "_class": "UIFontDescriptor",
          "attributes": {
            "name": "Sarabun-SemiBold",
            "size": 16
          }
        },
        "paragraphStyle": {
          "_class": "paragraphStyle"
        }
      },
      "verticalAlignment": 0
    },
    "windingRule": 1
  },
  "textBehaviour": 2
}